scrollstats/__init__.py
scrollstats/_version.py
scrollstats/_version.pyi
scrollstats/py.typed
scrollstats/delineation/__init__.py
scrollstats/delineation/array_types.py
scrollstats/delineation/line_smoother.py
scrollstats/delineation/raster_classifiers.py
scrollstats/delineation/raster_denoisers.py
scrollstats/delineation/ridge_area_raster.py
scrollstats/ridge_metrics/__init__.py
scrollstats/ridge_metrics/calc_ridge_metrics.py
scrollstats/ridge_metrics/data_extractors.py
scrollstats/ridge_metrics/ridge_amplitude.py
scrollstats/transecting/__init__.py
scrollstats/transecting/transect.py
scrollstats-0.1.2.dist-info/METADATA
scrollstats-0.1.2.dist-info/WHEEL
scrollstats-0.1.2.dist-info/licenses/LICENSE
scrollstats-0.1.2.dist-info/RECORD
