Metadata-Version: 2.4
Name: scrollstats
Version: 0.1.2
Summary: An open-source python library to calculate and extract morphometrics from scroll bar floodplains
Project-URL: Homepage, https://github.com/tamu-edu/scrollstats
Project-URL: Bug Tracker, https://github.com/tamu-edu/scrollstats/issues
Project-URL: Discussions, https://github.com/tamu-edu/scrollstats/discussions
Project-URL: Changelog, https://github.com/tamu-edu/scrollstats/releases
Author-email: Andrew Vanderheiden <andrewloyd19@gmail.com>
License-File: LICENSE
Classifier: Development Status :: 1 - Planning
Classifier: Intended Audience :: Developers
Classifier: Intended Audience :: Science/Research
Classifier: License :: OSI Approved :: MIT License
Classifier: Operating System :: OS Independent
Classifier: Programming Language :: Python
Classifier: Programming Language :: Python :: 3
Classifier: Programming Language :: Python :: 3 :: Only
Classifier: Programming Language :: Python :: 3.10
Classifier: Programming Language :: Python :: 3.11
Classifier: Programming Language :: Python :: 3.12
Classifier: Programming Language :: Python :: 3.13
Classifier: Topic :: Scientific/Engineering
Classifier: Typing :: Typed
Requires-Python: >=3.10
Requires-Dist: geopandas
Requires-Dist: matplotlib
Requires-Dist: nptyping
Requires-Dist: numba
Requires-Dist: rasterio
Requires-Dist: scipy
Requires-Dist: tqdm
Provides-Extra: dev
Requires-Dist: nox; extra == 'dev'
Requires-Dist: pytest-cov>=3; extra == 'dev'
Requires-Dist: pytest>=6; extra == 'dev'
Provides-Extra: docs
Requires-Dist: furo>=2023.08.17; extra == 'docs'
Requires-Dist: ipykernel; extra == 'docs'
Requires-Dist: myst-parser>=0.13; extra == 'docs'
Requires-Dist: nbsphinx; extra == 'docs'
Requires-Dist: sphinx-autodoc-typehints; extra == 'docs'
Requires-Dist: sphinx-copybutton; extra == 'docs'
Requires-Dist: sphinx>=7.0; extra == 'docs'
Provides-Extra: test
Requires-Dist: pytest-cov>=3; extra == 'test'
Requires-Dist: pytest>=6; extra == 'test'
